_CVXcanon.so
_version__.py
canonInterface.py
CVXcanon.py
CVXcanon-0.0.23.3.dist-info/DESCRIPTION.rst
CVXcanon-0.0.23.3.dist-info/METADATA
CVXcanon-0.0.23.3.dist-info/metadata.json
CVXcanon-0.0.23.3.dist-info/RECORD
CVXcanon-0.0.23.3.dist-info/top_level.txt
CVXcanon-0.0.23.3.dist-info/WHEEL
