Metadata-Version: 2.0
Name: CVXcanon
Version: 0.0.23.3
Summary: A low-level library to perform the matrix building step in cvxpy, a convex optimization modeling software.
Home-page: https://github.com/jacklzhu/CVXcanon
Author: Jack Zhu, John Miller, Paul Quigley
Author-email: jackzhu@stanford.edu, millerjp@stanford.edu, piq93@stanford.edu
License: GPLv3
Platform: UNKNOWN
Requires-Dist: numpy
Requires-Dist: scipy
